preprocessing_functions/__init__.py
preprocessing_functions/img_to_array.py
preprocessing_functions/inception.py
preprocessing_functions/load_img.py
preprocessing_functions-0.1.1.dist-info/WHEEL
preprocessing_functions-0.1.1.dist-info/METADATA
preprocessing_functions-0.1.1.dist-info/RECORD
